edubase_api/__init__.py
edubase_api/py.typed
edubase_api-0.3.2.dist-info/METADATA
edubase_api-0.3.2.dist-info/WHEEL
edubase_api-0.3.2.dist-info/licenses/LICENSE
edubase_api-0.3.2.dist-info/RECORD
